{"input_type": "wsi", "otsu_ratio": 0.0, "curvature_weight": 0.0, "min_size": 1, "max_size": 5, "ms_kernel": 0, "declump_type": 0, "levelset_num_iters": 0, "mpp": 0.25, "image_width": 69167, "image_height": 42645, "tile_minx": 52001, "tile_miny": 4001, "tile_width": 4000, "tile_height": 4000, "patch_minx": 52001, "patch_miny": 4001, "patch_width": 4000, "patch_height": 4000, "output_level": "mask", "out_file_prefix": "52001_4001_4000_4000_0.25", "subject_id": "3908-multires", "case_id": "3908-multires", "analysis_id": "v8_10x20x_comb_CD3-Double_Negative_T_cell-Yellow", "analysis_desc": "v8_10x20x_comb_"}